flyingfish/__init__.py
flyingfish/timeseries.py
flyingfish/EDA/__init__.py
flyingfish/EDA/estimates_location.py
flyingfish/EDA/estimates_shape.py
flyingfish/EDA/estimates_variability.py
flyingfish/EDA/multivariate.py
flyingfish/EDA/outlier_analysis.py
flyingfish/EDA/plotting_positions.py
flyingfish/EDA/quality_investigation.py
flyingfish/FDM/Model.py
flyingfish/FDM/__init__.py
flyingfish-0.0.3.dist-info/LICENSE
flyingfish-0.0.3.dist-info/METADATA
flyingfish-0.0.3.dist-info/WHEEL
flyingfish-0.0.3.dist-info/top_level.txt
flyingfish-0.0.3.dist-info/RECORD
