Metadata-Version: 2.1
Name: flyingfish
Version: 0.0.3
Summary: An open source library for common hydrological and meteorological issues
Author-email: Lena Marie Müller <lenamariemue@gmail.com>
Classifier: Programming Language :: Python :: 3
Classifier: Programming Language :: Python :: 3.10
Classifier: License :: OSI Approved :: MIT License
Classifier: Operating System :: OS Independent
Requires-Python: >=3.7
License-File: LICENSE
